{
	"mapPath": "campaign/Tutorial5",
	"mapName": "Tutorial 5",
	"neutralMines": [
		{
			"posX": 13,
			"posY": 1,
			"life": 100,
			"materials": 35,
			"active": true
		},
		{
			"posX": 2,
			"posY": 7,
			"life": 100,
			"materials": 35,
			"active": true
		}
	],
	"neutralBuildings": [
		{
			"posX": 3,
			"posY": 2,
			"life": 100,
			"materials": 35,
			"active": true,
			"extraLifeRegen": true
		}
	], "players": [{
		"allowedBuildingUpgrades":{"population":true,"materials":true,"defense":true,"range":true},
		"units": [],
		"buildings": [{
			"tag": "teamBuilding",
			"posX": 7,
			"posY": 4,
			"life": 100,
			"materials": 35,
			"active": true
		}]
	}, {
		"mines": [],
		"buildings": [{
			"tag": "enemyBuilding",
			"posX": 13,
			"posY": 7,
			"life": 100,
			"materials": 15,
			"active": true
		}],
		"allowedBuildingUpgrades":{"population":true,"materials":true,"defense":true,"range":true},
		"units": [{
			"tag": "enemyArcher",
			"posX": 9,
			"posY": 4,
			"life": 95,
			"type": {
				"seniority": 0,
				"primary": 2,
				"secondaries": []
			},
			"active": true,
			"lookingRight": false
		},
		{
			"tag": "enemyWarrior",
			"posX": 11,
			"posY": 4,
			"life": 95,
			"type": {
				"seniority": 0,
				"primary": 0,
				"secondaries": []
			},
			"active": true,
			"lookingRight": false
		}]
	}],"featureFlags":{"experience":false,"tacticPoints":false,"battlePoints":false,"randomness":false, "buildingUpgrades": true}
}